gs/__init__.py
pyGoldenShark-0.0.1.dist-info/LICENSE
pyGoldenShark-0.0.1.dist-info/METADATA
pyGoldenShark-0.0.1.dist-info/WHEEL
pyGoldenShark-0.0.1.dist-info/top_level.txt
pyGoldenShark-0.0.1.dist-info/RECORD
