Metadata-Version: 2.1
Name: pyGoldenShark
Version: 0.0.1
Summary: A library with many functions for managing, analyzing and pricing financial assets
Home-page: https://github.com/ViniAbreu/pyGoldenShark
Author: Weslley Capelari & Vinicius Abreu
Author-email: author@example.com
License: UNKNOWN
Project-URL: Bug Tracker, https://github.com/ViniAbreu/pyGoldenShark/issues
Platform: UNKNOWN
Classifier: Programming Language :: Python :: 3
Classifier: License :: OSI Approved :: MIT License
Classifier: Operating System :: OS Independent
Requires-Python: >=3.6
